{
    "data": {
        "id": 1838523,
        "port": {
            "id": 220,
            "name": "ReactorTemperature_SptExt",
            "unit": "Celsius"
        },
        "realTime": false,
        "values": [
            [
                1.2571861111111113E-4,
                0.0
            ],
            [
                0.24991916833333336,
                0.0
            ],
            [
                0.4999447761111111,
                0.0
            ],
            [
                0.7499704744444444,
                0.0
            ],
            [
                0.9999965141666667,
                0.0
            ],
            [
                1.2500227986111112,
                0.0
            ],
            [
                1.5000468505555555,
                0.0
            ],
            [
                1.7500714019444445,
                0.0
            ],
            [
                1.9792614825,
                0.0
            ],
            [
                1.9803727058333334,
                5.0
            ],
            [
                2.1612248530555553,
                5.0
            ],
            [
                2.1617804680555555,
                2.0
            ],
            [
                2.173726155833333,
                2.0
            ],
            [
                2.1745595805555555,
                3.0
            ],
            [
                2.189005489722222,
                3.0
            ],
            [
                2.189005489722222,
                2.0
            ],
            [
                2.1931726044444444,
                2.0
            ],
            [
                2.1937282180555555,
                3.0
            ],
            [
                2.1987287358333334,
                3.0
            ],
            [
                2.1990065433333332,
                5.0
            ],
            [
                2.2153971402777777,
                5.0
            ],
            [
                2.2165083683333333,
                6.0
            ],
            [
                2.2487339841666665,
                6.0
            ],
            [
                2.249845211388889,
                7.0
            ],
            [
                2.254290130555556,
                7.0
            ],
            [
                2.255401350277778,
                8.0
            ],
            [
                2.2570681880555554,
                8.0
            ],
            [
                2.2570681880555554,
                9.0
            ],
            [
                2.259012833611111,
                9.0
            ],
            [
                2.2601240625,
                10.0
            ],
            [
                2.4279194452777775,
                10.0
            ],
            [
                2.428752858888889,
                9.0
            ],
            [
                2.4320865191666665,
                9.0
            ],
            [
                2.432364328611111,
                8.0
            ],
            [
                2.6835011127777775,
                8.0
            ],
            [
                2.9332471080555553,
                8.0
            ],
            [
                3.183272650833333,
                8.0
            ],
            [
                3.4332988383333336,
                8.0
            ],
            [
                3.68332473,
                8.0
            ],
            [
                3.8994585744444445,
                8.0
            ],
            [
                3.9002919944444447,
                7.0
            ],
            [
                4.151427426666667,
                7.0
            ],
            [
                4.401451264444445,
                7.0
            ],
            [
                4.651476285277778,
                7.0
            ],
            [
                4.901502273055556,
                7.0
            ],
            [
                5.151528325555555,
                7.0
            ],
            [
                5.4015538175,
                7.0
            ],
            [
                5.651576688333334,
                7.0
            ],
            [
                5.901323229722222,
                7.0
            ],
            [
                6.151349006388889,
                7.0
            ],
            [
                6.264165792222222,
                7.0
            ]
        ],
        "xmin": 0.0,
        "xmax": 6.26416579222222,
        "ymin": 0.0,
        "ymax": 10.0,
        "reactor": {
            "id": 1,
            "name": "Fermenter 1"
        },
        "device": {
            "id": 187,
            "name": "Labfors_F1"
        },
        "subDevice": {
            "id": 46,
            "name": "SetpointSubDev"
        },
        "modifiedTimestamp": "2022-11-30T19:14:34"
    }
}